veryfi_test/__init__.py
veryfi_test/config.py
veryfi_test/extract_cli.py
veryfi_test/extractor.py
veryfi_test/ocr_cli.py
veryfi_test-0.2.0.dist-info/licenses/LICENSE
veryfi_test-0.2.0.dist-info/METADATA
veryfi_test-0.2.0.dist-info/WHEEL
veryfi_test-0.2.0.dist-info/entry_points.txt
veryfi_test-0.2.0.dist-info/top_level.txt
veryfi_test-0.2.0.dist-info/RECORD
