Metadata-Version: 2.4
Name: veryfi-test
Version: 0.2.0
Summary: Utilities for Veryfi Data Annotations Engineer test
Author: Omar Zapata
Project-URL: Homepage, https://www.veryfi.com/
Requires-Python: >=3.11
License-File: LICENSE
Requires-Dist: veryfi==5.0.0
Dynamic: license-file
